CHANGELOG.rst
LICENSE
MANIFEST.in
README.rst
setup.cfg
setup.py
scanpointgenerator/__init__.py
scanpointgenerator/compat.py
scanpointgenerator/plotgenerator.py
scanpointgenerator/version.py
scanpointgenerator.egg-info/PKG-INFO
scanpointgenerator.egg-info/SOURCES.txt
scanpointgenerator.egg-info/dependency_links.txt
scanpointgenerator.egg-info/not-zip-safe
scanpointgenerator.egg-info/top_level.txt
scanpointgenerator/core/__init__.py
scanpointgenerator/core/compoundgenerator.py
scanpointgenerator/core/dimension.py
scanpointgenerator/core/excluder.py
scanpointgenerator/core/generator.py
scanpointgenerator/core/mutator.py
scanpointgenerator/core/point.py
scanpointgenerator/core/random.py
scanpointgenerator/core/roi.py
scanpointgenerator/excluders/__init__.py
scanpointgenerator/excluders/roiexcluder.py
scanpointgenerator/excluders/squashingexcluder.py
scanpointgenerator/generators/__init__.py
scanpointgenerator/generators/arraygenerator.py
scanpointgenerator/generators/concatgenerator.py
scanpointgenerator/generators/linegenerator.py
scanpointgenerator/generators/lissajousgenerator.py
scanpointgenerator/generators/spiralgenerator.py
scanpointgenerator/generators/staticpointgenerator.py
scanpointgenerator/generators/zipgenerator.py
scanpointgenerator/mutators/__init__.py
scanpointgenerator/mutators/randomoffsetmutator.py
scanpointgenerator/rois/__init__.py
scanpointgenerator/rois/circular_roi.py
scanpointgenerator/rois/elliptical_roi.py
scanpointgenerator/rois/linear_roi.py
scanpointgenerator/rois/point_roi.py
scanpointgenerator/rois/polygonal_roi.py
scanpointgenerator/rois/rectangular_roi.py
scanpointgenerator/rois/sector_roi.py
tests/__init__.py
tests/test_util.py
tests/test_core/__init__.py
tests/test_core/test_compoundgenerator.py
tests/test_core/test_compoundgenerator_performance.py
tests/test_core/test_dimension.py
tests/test_core/test_excluder.py
tests/test_core/test_generator.py
tests/test_core/test_get_points.py
tests/test_core/test_get_points_performance.py
tests/test_core/test_mutator.py
tests/test_core/test_random.py
tests/test_core/test_roi.py
tests/test_excluders/__init__.py
tests/test_excluders/test_roiexcluder.py
tests/test_excluders/test_squashingexcluder.py
