Metadata-Version: 1.1
Name: scanpointgenerator
Version: 3.1
Summary: Python generators for malcolm and GDA scans
Home-page: https://github.com/dls_controls/scanpointgenerator
Author: Tom Cobb
Author-email: tom.cobb@diamond.ac.uk
License: APACHE
Platform: UNKNOWN
Classifier: Development Status :: 3 - Alpha
Classifier: Intended Audience :: Developers
Classifier: Natural Language :: English
Classifier: Operating System :: POSIX :: Linux
Classifier: Programming Language :: Python :: 2.7
